[
  { "key": "example", "label": "Example Group", "label_zh": "示例组", "file": "example.json" },
  { "key": "MBZUI", "label": "MBZUI", "label_zh": "穆罕默德·本·扎耶德人工智能大学", "file": "MBZUI.json" },
  { "key": "Xiao_Xiang_Zhu", "label": "Xiao Xiang Zhu", "label_zh": "朱晓香", "file": "Xiao_Xiang_Zhu.json", "auto": true, "authors": ["Xiao Xiang Zhu", "Xiaoxiang Zhu"] },
  { "key": "xian-sun", "label": "Xian Sun", "label_zh": "孙显", "file": "xian-sun.json", "auto": true, "authors": ["Xian Sun"] },
  { "key": "yanfei-zhong", "label": "Yanfei Zhong", "label_zh": "钟燕飞", "file": "yanfei-zhong.json", "auto": true, "authors": ["Yanfei Zhong"] },
  { "key": "zhenwei-shi", "label": "Zhenwei Shi", "label_zh": "史振威", "file": "zhenwei-shi.json", "auto": true, "authors": ["Zhenwei Shi"] },
  { "key": "guisong-xia", "label": "Gui-Song Xia", "label_zh": "夏桂松", "file": "guisong-xia.json", "auto": true, "authors": ["Gui-Song Xia", "Gui-song Xia", "Guisong Xia"] },
  { "key": "bo-du", "label": "Bo Du", "label_zh": "杜博", "file": "bo-du.json", "auto": true, "authors": ["Bo Du"] },
  { "key": "junwei-han", "label": "Junwei Han", "label_zh": "韩军伟", "file": "junwei-han.json", "auto": true, "authors": ["Junwei Han"] },
  { "key": "yansheng-li", "label": "Yansheng Li", "label_zh": "李彦胜", "file": "yansheng-li.json", "auto": true, "authors": ["Yansheng Li"] }
]
